Workbook

Sheet Your Numbers
A1: Your Numbers — what you need to charge per billable hour
A2: Start here. Every other sheet uses the Target hourly rate from this page.
A3: Yellow cells are inputs — change them. Green cells are results (formulas).
A5: Annual take-home pay goal (what you want to pay yourself) | B5: 65000 | C5: Be honest — this is your salary, not the business's revenue.
A6: Tax set-aside (% of profit) — ask your accountant | B6: 0.25
A7: Annual business costs (vehicle, insurance, supplies, equipment, software, phone, marketing) | B7: 20000
A8: Working weeks per year (after vacation, weather, sick days) | B8: 48
A9: Billable hours per week (paid, on-site time — not driving or quoting) | B9: 28 | C9: Most solo operators bill 25–32 hours in a 45–50 hour work week.
A11: Profit needed before tax | B11: =B5/(1-B6)
A12: Revenue needed per year | B12: =B11+B7
A13: Billable hours per year | B13: =B8*B9
A14: Minimum hourly rate (break-even on your goal) | B14: =IF(B13>0,B12/B13,0)
A15: Buffer for slow weeks, callbacks, and price creep (%) | B15: 0.15
A16: TARGET HOURLY RATE (used by the other sheets) | B16: =B14*(1+B15)
A17: Revenue needed per working week | B17: =IF(B8>0,B12/B8,0)

Sheet Task Pricing
A1: Handyman Task Pricing Library
A2: Edit hours to match YOUR pace. Price = typical hours × rate + materials × (1 + markup).
A3: Yellow cells are inputs — change them. Green cells are results (formulas).
A4: Target hourly rate | B4: ='Your Numbers'!$B$16
A5: Materials markup (covers pickup time, returns, waste) | B5: 0.2
A6: Minimum per-visit charge | B6: 150
A7: Supply-run / trip charge (if you buy materials) | B7: 25
A9: Task | B9: Category | C9: Hours (low) | D9: Hours (typical) | E9: Typical materials $ | F9: Labor price | G9: Price incl. materials | H9: Notes
A10: TV mount — up to 65in, drywall/studs | B10: Mounting | C10: 0.75 | D10: 1.25 | E10: 0 | F10: =D10*$B$4 | G10: =F10+E10*(1+$B$5) | H10: Client supplies mount; cord concealment extra
A11: TV mount — cord concealment kit (in-wall rated) | B11: Mounting | C11: 0.75 | D11: 1 | E11: 30 | F11: =D11*$B$4 | G11: =F11+E11*(1+$B$5) | H11: Use an in-wall rated kit; no extension cords in walls
A12: Hang shelves (per 3 shelves) | B12: Mounting | C12: 0.5 | D12: 1 | E12: 0 | F12: =D12*$B$4 | G12: =F12+E12*(1+$B$5) | H12: Anchors vs studs changes time
A13: Hang pictures / mirrors (per 5 items) | B13: Mounting | C13: 0.5 | D13: 1 | E13: 5 | F13: =D13*$B$4 | G13: =F13+E13*(1+$B$5) | H13: Heavy mirrors: French cleat
A14: Curtain rods (per window) | B14: Mounting | C14: 0.33 | D14: 0.5 | E14: 0 | F14: =D14*$B$4 | G14: =F14+E14*(1+$B$5)
A15: Blinds install (per window, inside mount) | B15: Mounting | C15: 0.33 | D15: 0.5 | E15: 0 | F15: =D15*$B$4 | G15: =F15+E15*(1+$B$5)
A16: Furniture assembly — small (nightstand, chair) | B16: Assembly | C16: 0.5 | D16: 0.75 | E16: 0 | F16: =D16*$B$4 | G16: =F16+E16*(1+$B$5)
A17: Furniture assembly — large (dresser, bed frame) | B17: Assembly | C17: 1.5 | D17: 2.5 | E17: 0 | F17: =D17*$B$4 | G17: =F17+E17*(1+$B$5) | H17: Wardrobes/PAX-style: 3–5 hrs
A18: Drywall patch — small (under 6in) | B18: Drywall & paint | C18: 0.75 | D18: 1 | E18: 10 | F18: =D18*$B$4 | G18: =F18+E18*(1+$B$5) | H18: Needs a second visit or fast-set compound
A19: Drywall patch — medium (6–16in) | B19: Drywall & paint | C19: 1.5 | D19: 2.5 | E19: 20 | F19: =D19*$B$4 | G19: =F19+E19*(1+$B$5) | H19: Often 2 visits for mud + paint
A20: Touch-up paint (per wall) | B20: Drywall & paint | C20: 0.75 | D20: 1 | E20: 0 | F20: =D20*$B$4 | G20: =F20+E20*(1+$B$5) | H20: Client supplies paint; color match not guaranteed
A21: Caulk tub or shower surround | B21: Bath & kitchen | C21: 1 | D21: 1.5 | E21: 15 | F21: =D21*$B$4 | G21: =F21+E21*(1+$B$5) | H21: Old caulk removal is most of the time
A22: Replace toilet fill valve / flapper | B22: Bath & kitchen | C22: 0.5 | D22: 0.75 | E22: 20 | F22: =D22*$B$4 | G22: =F22+E22*(1+$B$5) | H22: Check your state's plumbing license limits
A23: Replace kitchen/bath faucet (same footprint) | B23: Bath & kitchen | C23: 1 | D23: 1.5 | E23: 0 | F23: =D23*$B$4 | G23: =F23+E23*(1+$B$5) | H23: Client supplies faucet; seized nuts add time
A24: Replace garbage disposal (like for like) | B24: Bath & kitchen | C24: 1 | D24: 1.5 | E24: 0 | F24: =D24*$B$4 | G24: =F24+E24*(1+$B$5) | H24: Check license limits
A25: Replace toilet (like for like) | B25: Bath & kitchen | C25: 1.5 | D25: 2 | E25: 15 | F25: =D25*$B$4 | G25: =F25+E25*(1+$B$5) | H25: Wax ring/bolts; haul-away extra
A26: Regrout small area (under 10 sq ft) | B26: Bath & kitchen | C26: 2 | D26: 3 | E26: 20 | F26: =D26*$B$4 | G26: =F26+E26*(1+$B$5)
A27: Swap light fixture (existing box) | B27: Electrical (where allowed) | C27: 0.75 | D27: 1 | E27: 0 | F27: =D27*$B$4 | G27: =F27+E27*(1+$B$5) | H27: Many states require a licensed electrician — check first
A28: Swap ceiling fan (existing fan-rated box) | B28: Electrical (where allowed) | C28: 1 | D28: 1.5 | E28: 0 | F28: =D28*$B$4 | G28: =F28+E28*(1+$B$5) | H28: Confirm box is fan-rated
A29: Replace smoke/CO detectors (per unit) | B29: Electrical (where allowed) | C29: 0.25 | D29: 0.33 | E29: 0 | F29: =D29*$B$4 | G29: =F29+E29*(1+$B$5) | H29: Battery units; hardwired = check license
A30: Replace interior door hardware (per door) | B30: Doors & windows | C30: 0.33 | D30: 0.5 | E30: 0 | F30: =D30*$B$4 | G30: =F30+E30*(1+$B$5)
A31: Hang pre-hung interior door | B31: Doors & windows | C31: 2 | D31: 3 | E31: 0 | F31: =D31*$B$4 | G31: =F31+E31*(1+$B$5) | H31: Door supplied by client; trim extra
A32: Adjust sticking door / strike plate | B32: Doors & windows | C32: 0.5 | D32: 0.75 | E32: 5 | F32: =D32*$B$4 | G32: =F32+E32*(1+$B$5)
A33: Weatherstrip exterior door | B33: Doors & windows | C33: 0.75 | D33: 1 | E33: 25 | F33: =D33*$B$4 | G33: =F33+E33*(1+$B$5)
A34: Replace window screen (rescreen) | B34: Doors & windows | C34: 0.33 | D34: 0.5 | E34: 10 | F34: =D34*$B$4 | G34: =F34+E34*(1+$B$5)
A35: Gutter cleaning — 1 story (per 100 lf) | B35: Exterior | C35: 1 | D35: 1.25 | E35: 0 | F35: =D35*$B$4 | G35: =F35+E35*(1+$B$5) | H35: Ladder safety; 2-story needs a second person
A36: Fence board / picket repair (per 5 boards) | B36: Exterior | C36: 0.75 | D36: 1 | E36: 25 | F36: =D36*$B$4 | G36: =F36+E36*(1+$B$5)
A37: Deck board replacement (per board) | B37: Exterior | C37: 0.5 | D37: 0.75 | E37: 20 | F37: =D37*$B$4 | G37: =F37+E37*(1+$B$5) | H37: Check joists while you're there
A38: Pressure-treat / seal small deck (per 100 sq ft) | B38: Exterior | C38: 1 | D38: 1.5 | E38: 25 | F38: =D38*$B$4 | G38: =F38+E38*(1+$B$5)
A39: Baby-proofing package (gates, latches, anchors) | B39: Misc | C39: 1.5 | D39: 2.5 | E39: 0 | F39: =D39*$B$4 | G39: =F39+E39*(1+$B$5) | H39: Client supplies products

Sheet Quote Builder
A1: Handyman Quote Builder
A2: Pick tasks from the dropdown, enter quantities. Minimum visit charge applies.
A3: Yellow cells are inputs — change them. Green cells are results (formulas).
A5: Task (pick from list) | B5: Qty | C5: Hours | D5: Labor $ | E5: Materials $ | F5: Line total $
A6: TV mount — up to 65in, drywall/studs | B6: 1 | C6: =IF(A6="","",VLOOKUP(A6,'Task Pricing'!$A$10:$H$39,4,FALSE)*B6) | D6: =IF(A6="","",C6*'Task Pricing'!$B$4) | E6: =IF(A6="","",VLOOKUP(A6,'Task Pricing'!$A$10:$H$39,5,FALSE)*B6*(1+'Task Pricing'!$B$5)) | F6: =IF(A6="","",D6+E6)
A7: Hang shelves (per 3 shelves) | B7: 1 | C7: =IF(A7="","",VLOOKUP(A7,'Task Pricing'!$A$10:$H$39,4,FALSE)*B7) | D7: =IF(A7="","",C7*'Task Pricing'!$B$4) | E7: =IF(A7="","",VLOOKUP(A7,'Task Pricing'!$A$10:$H$39,5,FALSE)*B7*(1+'Task Pricing'!$B$5)) | F7: =IF(A7="","",D7+E7)
A8: Caulk tub or shower surround | B8: 1 | C8: =IF(A8="","",VLOOKUP(A8,'Task Pricing'!$A$10:$H$39,4,FALSE)*B8) | D8: =IF(A8="","",C8*'Task Pricing'!$B$4) | E8: =IF(A8="","",VLOOKUP(A8,'Task Pricing'!$A$10:$H$39,5,FALSE)*B8*(1+'Task Pricing'!$B$5)) | F8: =IF(A8="","",D8+E8)
C9: =IF(A9="","",VLOOKUP(A9,'Task Pricing'!$A$10:$H$39,4,FALSE)*B9) | D9: =IF(A9="","",C9*'Task Pricing'!$B$4) | E9: =IF(A9="","",VLOOKUP(A9,'Task Pricing'!$A$10:$H$39,5,FALSE)*B9*(1+'Task Pricing'!$B$5)) | F9: =IF(A9="","",D9+E9)
C10: =IF(A10="","",VLOOKUP(A10,'Task Pricing'!$A$10:$H$39,4,FALSE)*B10) | D10: =IF(A10="","",C10*'Task Pricing'!$B$4) | E10: =IF(A10="","",VLOOKUP(A10,'Task Pricing'!$A$10:$H$39,5,FALSE)*B10*(1+'Task Pricing'!$B$5)) | F10: =IF(A10="","",D10+E10)
C11: =IF(A11="","",VLOOKUP(A11,'Task Pricing'!$A$10:$H$39,4,FALSE)*B11) | D11: =IF(A11="","",C11*'Task Pricing'!$B$4) | E11: =IF(A11="","",VLOOKUP(A11,'Task Pricing'!$A$10:$H$39,5,FALSE)*B11*(1+'Task Pricing'!$B$5)) | F11: =IF(A11="","",D11+E11)
C12: =IF(A12="","",VLOOKUP(A12,'Task Pricing'!$A$10:$H$39,4,FALSE)*B12) | D12: =IF(A12="","",C12*'Task Pricing'!$B$4) | E12: =IF(A12="","",VLOOKUP(A12,'Task Pricing'!$A$10:$H$39,5,FALSE)*B12*(1+'Task Pricing'!$B$5)) | F12: =IF(A12="","",D12+E12)
C13: =IF(A13="","",VLOOKUP(A13,'Task Pricing'!$A$10:$H$39,4,FALSE)*B13) | D13: =IF(A13="","",C13*'Task Pricing'!$B$4) | E13: =IF(A13="","",VLOOKUP(A13,'Task Pricing'!$A$10:$H$39,5,FALSE)*B13*(1+'Task Pricing'!$B$5)) | F13: =IF(A13="","",D13+E13)
C14: =IF(A14="","",VLOOKUP(A14,'Task Pricing'!$A$10:$H$39,4,FALSE)*B14) | D14: =IF(A14="","",C14*'Task Pricing'!$B$4) | E14: =IF(A14="","",VLOOKUP(A14,'Task Pricing'!$A$10:$H$39,5,FALSE)*B14*(1+'Task Pricing'!$B$5)) | F14: =IF(A14="","",D14+E14)
C15: =IF(A15="","",VLOOKUP(A15,'Task Pricing'!$A$10:$H$39,4,FALSE)*B15) | D15: =IF(A15="","",C15*'Task Pricing'!$B$4) | E15: =IF(A15="","",VLOOKUP(A15,'Task Pricing'!$A$10:$H$39,5,FALSE)*B15*(1+'Task Pricing'!$B$5)) | F15: =IF(A15="","",D15+E15)
C16: =IF(A16="","",VLOOKUP(A16,'Task Pricing'!$A$10:$H$39,4,FALSE)*B16) | D16: =IF(A16="","",C16*'Task Pricing'!$B$4) | E16: =IF(A16="","",VLOOKUP(A16,'Task Pricing'!$A$10:$H$39,5,FALSE)*B16*(1+'Task Pricing'!$B$5)) | F16: =IF(A16="","",D16+E16)
C17: =IF(A17="","",VLOOKUP(A17,'Task Pricing'!$A$10:$H$39,4,FALSE)*B17) | D17: =IF(A17="","",C17*'Task Pricing'!$B$4) | E17: =IF(A17="","",VLOOKUP(A17,'Task Pricing'!$A$10:$H$39,5,FALSE)*B17*(1+'Task Pricing'!$B$5)) | F17: =IF(A17="","",D17+E17)
A19: Total hours | C19: =SUM(C6:C17)
A20: Tasks subtotal | F20: =SUM(F6:F17)
A21: Supply-run charge? (Yes/No) | B21: No | F21: =IF(B21="Yes",'Task Pricing'!$B$7,0)
A22: Rush / after-hours uplift (%) | B22: 0 | F22: =SUM(D6:D17)*B22
A24: QUOTED PRICE | F24: =CEILING(MAX('Task Pricing'!$B$6,F20+F21+F22),5)
A25: Effective hourly (check vs target) | F25: =IF(C19>0,F24/C19,0)
A26: Status | F26: =IF(C19=0,"",IF(F25<'Task Pricing'!$B$4,"Below target — check hours","OK"))

Sheet Rate Card
A1: Handyman Rate Card
A2: Starting ranges only — prices vary a lot by region. Replace with your local numbers.
A4: Category | B4: Item | C4: Unit | D4: Low $ | E4: Target $ | F4: Your price $ | G4: Notes
A5: rates | B5: Minimum per-visit charge (includes first hour) | C5: visit | D5: 125 | E5: 175 | G5: Protects you on tiny jobs
A6: rates | B6: Hourly labor after first hour | C6: hour | D6: 65 | E6: 110 | G6: Solo handyman
A7: rates | B7: Supply run / materials pickup | C7: trip | D7: 20 | E7: 40 | G7: Plus materials at cost + markup
A8: rates | B8: Materials markup | C8: percent | D8: 15 | E8: 25 | G8: Percent over receipt
A9: rates | B9: Haul-away (small load) | C9: load | D9: 40 | E9: 90 | G9: Dump fees vary
A10: Mounting | B10: TV mount — up to 65in, drywall/studs | C10: task (min. visit charge applies) | D10: 65 | E10: 120 | G10: Client supplies mount; cord concealment extra
A11: Mounting | B11: TV mount — cord concealment kit (in-wall rated) | C11: task (min. visit charge applies) | D11: 95 | E11: 125 | G11: Use an in-wall rated kit; no extension cords in walls
A12: Mounting | B12: Hang shelves (per 3 shelves) | C12: task (min. visit charge applies) | D12: 45 | E12: 95 | G12: Anchors vs studs changes time
A13: Mounting | B13: Hang pictures / mirrors (per 5 items) | C13: task (min. visit charge applies) | D13: 50 | E13: 100 | G13: Heavy mirrors: French cleat
A14: Mounting | B14: Curtain rods (per window) | C14: task (min. visit charge applies) | D14: 30 | E14: 50
A15: Mounting | B15: Blinds install (per window, inside mount) | C15: task (min. visit charge applies) | D15: 30 | E15: 50
A16: Assembly | B16: Furniture assembly — small (nightstand, chair) | C16: task (min. visit charge applies) | D16: 45 | E16: 70
A17: Assembly | B17: Furniture assembly — large (dresser, bed frame) | C17: task (min. visit charge applies) | D17: 130 | E17: 240 | G17: Wardrobes/PAX-style: 3–5 hrs
A18: Drywall & paint | B18: Drywall patch — small (under 6in) | C18: task (min. visit charge applies) | D18: 75 | E18: 105 | G18: Needs a second visit or fast-set compound
A19: Drywall & paint | B19: Drywall patch — medium (6–16in) | C19: task (min. visit charge applies) | D19: 150 | E19: 260 | G19: Often 2 visits for mud + paint
A20: Drywall & paint | B20: Touch-up paint (per wall) | C20: task (min. visit charge applies) | D20: 65 | E20: 95 | G20: Client supplies paint; color match not guaranteed
A21: Bath & kitchen | B21: Caulk tub or shower surround | C21: task (min. visit charge applies) | D21: 100 | E21: 160 | G21: Old caulk removal is most of the time
A22: Bath & kitchen | B22: Replace toilet fill valve / flapper | C22: task (min. visit charge applies) | D22: 65 | E22: 90 | G22: Check your state's plumbing license limits
A23: Bath & kitchen | B23: Replace kitchen/bath faucet (same footprint) | C23: task (min. visit charge applies) | D23: 85 | E23: 145 | G23: Client supplies faucet; seized nuts add time
A24: Bath & kitchen | B24: Replace garbage disposal (like for like) | C24: task (min. visit charge applies) | D24: 85 | E24: 145 | G24: Check license limits
A25: Bath & kitchen | B25: Replace toilet (like for like) | C25: task (min. visit charge applies) | D25: 145 | E25: 205 | G25: Wax ring/bolts; haul-away extra
A26: Bath & kitchen | B26: Regrout small area (under 10 sq ft) | C26: task (min. visit charge applies) | D26: 190 | E26: 305
A27: Electrical (where allowed) | B27: Swap light fixture (existing box) | C27: task (min. visit charge applies) | D27: 65 | E27: 95 | G27: Many states require a licensed electrician — check first
A28: Electrical (where allowed) | B28: Swap ceiling fan (existing fan-rated box) | C28: task (min. visit charge applies) | D28: 85 | E28: 145 | G28: Confirm box is fan-rated
A29: Electrical (where allowed) | B29: Replace smoke/CO detectors (per unit) | C29: task (min. visit charge applies) | D29: 20 | E29: 30 | G29: Battery units; hardwired = check license
A30: Doors & windows | B30: Replace interior door hardware (per door) | C30: task (min. visit charge applies) | D30: 30 | E30: 50
A31: Doors & windows | B31: Hang pre-hung interior door | C31: task (min. visit charge applies) | D31: 170 | E31: 285 | G31: Door supplied by client; trim extra
A32: Doors & windows | B32: Adjust sticking door / strike plate | C32: task (min. visit charge applies) | D32: 50 | E32: 75
A33: Doors & windows | B33: Weatherstrip exterior door | C33: task (min. visit charge applies) | D33: 90 | E33: 120
A34: Doors & windows | B34: Replace window screen (rescreen) | C34: task (min. visit charge applies) | D34: 40 | E34: 60
A35: Exterior | B35: Gutter cleaning — 1 story (per 100 lf) | C35: task (min. visit charge applies) | D35: 85 | E35: 120 | G35: Ladder safety; 2-story needs a second person
A36: Exterior | B36: Fence board / picket repair (per 5 boards) | C36: task (min. visit charge applies) | D36: 90 | E36: 120
A37: Exterior | B37: Deck board replacement (per board) | C37: task (min. visit charge applies) | D37: 65 | E37: 90 | G37: Check joists while you're there
A38: Exterior | B38: Pressure-treat / seal small deck (per 100 sq ft) | C38: task (min. visit charge applies) | D38: 110 | E38: 170
A39: Misc | B39: Baby-proofing package (gates, latches, anchors) | C39: task (min. visit charge applies) | D39: 130 | E39: 240 | G39: Client supplies products
