Workbook

Sheet Your Numbers
A1: Your Numbers — what you need to charge per billable hour
A2: Start here. Every other sheet uses the Target hourly rate from this page.
A3: Yellow cells are inputs — change them. Green cells are results (formulas).
A5: Annual take-home pay goal (what you want to pay yourself) | B5: 50000 | C5: Be honest — this is your salary, not the business's revenue.
A6: Tax set-aside (% of profit) — ask your accountant | B6: 0.25
A7: Annual business costs (vehicle, insurance, supplies, equipment, software, phone, marketing) | B7: 14000
A8: Working weeks per year (after vacation, weather, sick days) | B8: 46
A9: Billable hours per week (paid, on-site time — not driving or quoting) | B9: 28 | C9: Most solo operators bill 25–32 hours in a 45–50 hour work week.
A11: Profit needed before tax | B11: =B5/(1-B6)
A12: Revenue needed per year | B12: =B11+B7
A13: Billable hours per year | B13: =B8*B9
A14: Minimum hourly rate (break-even on your goal) | B14: =IF(B13>0,B12/B13,0)
A15: Buffer for slow weeks, callbacks, and price creep (%) | B15: 0.15
A16: TARGET HOURLY RATE (used by the other sheets) | B16: =B14*(1+B15)
A17: Revenue needed per working week | B17: =IF(B8>0,B12/B8,0)

Sheet Package Menu
A1: Detail Package Menu — base prices (sedan)
A2: Edit to match your menu. Size and condition multipliers apply to price AND time.
A3: Yellow cells are inputs — change them. Green cells are results (formulas).
A5: Package | B5: Base price | C5: Base hours | D5: Includes
A6: Maintenance wash | B6: 75 | C6: 1 | D6: Hand wash, wheels/tires, windows, quick vacuum, wipe-down
A7: Interior detail | B7: 185 | C7: 2.5 | D7: Full vacuum, plastics, leather/fabric clean, glass, door jambs
A8: Exterior detail | B8: 150 | C8: 2 | D8: Foam wash, decon, wheels/wells, spray sealant, tire dressing
A9: Full detail | B9: 295 | C9: 4 | D9: Interior detail + exterior detail
A10: Paint enhancement | B10: 450 | C10: 6 | D10: Full detail exterior + 1-step polish + sealant
A11: Ceramic coating (trained only) | B11: 900 | C11: 10 | D11: Decon + polish + coating install; price by product
A13: Vehicle size | B13: Multiplier
A14: Coupe / sedan | B14: 1
A15: Small SUV / crossover | B15: 1.15
A16: Mid-size SUV / crew-cab pickup | B16: 1.25
A17: Full-size SUV / minivan / 3-row | B17: 1.4
A18: Oversized / work van | B18: 1.6
A20: Condition | B20: Multiplier
A21: Normal | B21: 1
A22: Dirty | B22: 1.2
A23: Extreme | B23: 1.5

Sheet Quote Builder
A1: Mobile Detailing Quote Builder
A2: Pick package, size, condition, add-ons.
A3: Yellow cells are inputs — change them. Green cells are results (formulas).
A4: Target hourly rate | B4: ='Your Numbers'!$B$16
A5: Package | B5: Full detail
A6: Vehicle size | B6: Small SUV / crossover
A7: Condition | B7: Normal
A8: Travel fee (outside free radius) | B8: 0
A10: Size multiplier | B10: =VLOOKUP(B6,'Package Menu'!$A$14:$B$18,2,FALSE)
A11: Condition multiplier | B11: =VLOOKUP(B7,'Package Menu'!$A$21:$B$23,2,FALSE)
A12: Package price (adjusted) | B12: =VLOOKUP(B5,'Package Menu'!$A$6:$C$11,2,FALSE)*B10*B11
A13: Package hours (adjusted) | B13: =VLOOKUP(B5,'Package Menu'!$A$6:$C$11,3,FALSE)*B10*B11
A15: Add-on | B15: Qty (0/1) | C15: Price | D15: Hours | E15: Line $ | F15: Line hrs
A16: Pet hair removal | B16: 0 | C16: 60 | D16: 0.75 | E16: =B16*C16 | F16: =B16*D16
A17: Seat shampoo / hot-water extraction | B17: 0 | C17: 90 | D17: 1 | E17: =B17*C17 | F17: =B17*D17
A18: Carpet & mat extraction | B18: 0 | C18: 60 | D18: 0.75 | E18: =B18*C18 | F18: =B18*D18
A19: Leather clean & condition | B19: 0 | C19: 60 | D19: 0.5 | E19: =B19*C19 | F19: =B19*D19
A20: Engine bay clean | B20: 0 | C20: 60 | D20: 0.5 | E20: =B20*C20 | F20: =B20*D20
A21: Headlight restoration (pair) | B21: 0 | C21: 90 | D21: 0.75 | E21: =B21*C21 | F21: =B21*D21
A22: Odor treatment (enzyme + ozone) | B22: 0 | C22: 90 | D22: 0.5 | E22: =B22*C22 | F22: =B22*D22
A23: Clay bar + iron decon (add to wash) | B23: 0 | C23: 70 | D23: 0.75 | E23: =B23*C23 | F23: =B23*D23
A24: Sand / salt / heavy soil surcharge | B24: 0 | C24: 50 | D24: 0.5 | E24: =B24*C24 | F24: =B24*D24
A26: QUOTED PRICE | B26: =CEILING(B12+SUM(E16:E24)+B8,5)
A27: Estimated hours | B27: =B13+SUM(F16:F24)
A28: Effective hourly | B28: =IF(B27>0,B26/B27,0)
A29: Status | B29: =IF(B28<B4,"Below target — add size/condition surcharge or raise base price","OK")

Sheet Rate Card
A1: Mobile Detailing Rate Card
A2: Starting ranges only — prices vary a lot by region. Replace with your local numbers.
A4: Category | B4: Item | C4: Unit | D4: Low $ | E4: Target $ | F4: Your price $ | G4: Notes
A5: package (sedan) | B5: Maintenance wash | C5: vehicle | D5: 60 | E5: 75 | G5: Hand wash, wheels/tires, windows, quick vacuum, wipe-down
A6: package (sedan) | B6: Interior detail | C6: vehicle | D6: 150 | E6: 185 | G6: Full vacuum, plastics, leather/fabric clean, glass, door jambs
A7: package (sedan) | B7: Exterior detail | C7: vehicle | D7: 120 | E7: 150 | G7: Foam wash, decon, wheels/wells, spray sealant, tire dressing
A8: package (sedan) | B8: Full detail | C8: vehicle | D8: 235 | E8: 295 | G8: Interior detail + exterior detail
A9: package (sedan) | B9: Paint enhancement | C9: vehicle | D9: 360 | E9: 450 | G9: Full detail exterior + 1-step polish + sealant
A10: package (sedan) | B10: Ceramic coating (trained only) | C10: vehicle | D10: 720 | E10: 900 | G10: Decon + polish + coating install; price by product
A11: size multiplier | B11: Small SUV / crossover | C11: multiplier | G11: Multiply package price by 1.15
A12: size multiplier | B12: Mid-size SUV / crew-cab pickup | C12: multiplier | G12: Multiply package price by 1.25
A13: size multiplier | B13: Full-size SUV / minivan / 3-row | C13: multiplier | G13: Multiply package price by 1.4
A14: size multiplier | B14: Oversized / work van | C14: multiplier | G14: Multiply package price by 1.6
A15: add-on | B15: Pet hair removal | C15: each | D15: 45 | E15: 60
A16: add-on | B16: Seat shampoo / hot-water extraction | C16: each | D16: 70 | E16: 90
A17: add-on | B17: Carpet & mat extraction | C17: each | D17: 45 | E17: 60
A18: add-on | B18: Leather clean & condition | C18: each | D18: 45 | E18: 60
A19: add-on | B19: Engine bay clean | C19: each | D19: 45 | E19: 60
A20: add-on | B20: Headlight restoration (pair) | C20: each | D20: 70 | E20: 90
A21: add-on | B21: Odor treatment (enzyme + ozone) | C21: each | D21: 70 | E21: 90
A22: add-on | B22: Clay bar + iron decon (add to wash) | C22: each | D22: 55 | E22: 70
A23: add-on | B23: Sand / salt / heavy soil surcharge | C23: each | D23: 40 | E23: 50
A24: policy | B24: Travel fee beyond free radius | C24: trip | D24: 15 | E24: 35 | G24: Free radius typically 10–15 miles
A25: policy | B25: Maintenance plan (every 2–4 weeks) | C25: visit | D25: 60 | E25: 90 | G25: Only after an initial full or interior detail
