Workbook

Sheet Dashboard
A1: Weekly Money Dashboard
A2: Fill in the Job Log and Expenses tabs; this page updates itself. Clear the example rows first.
A3: Yellow cells are inputs — change them. Green cells are results (formulas).
A5: Tax set-aside (% of profit) — ask your accountant | B5: 0.25
A6: Your target profit per hour (from the Job Pricing Calculator) | B6: 75
A8: MONEY IN (jobs) | B8: =SUM('Job Log'!D6:D65)
A9: Jobs completed | B9: =COUNT('Job Log'!D6:D65)
A10: Average job price | B10: =IF(B9>0,B8/B9,0)
A12: Job costs (materials + other job costs) | B12: =SUM('Job Log'!E6:F65)
A13: Business expenses | B13: =SUM(Expenses!D6:D65)
A14: MONEY OUT (total) | B14: =B12+B13
A16: Profit before tax | B16: =B8-B14
A17: Set aside for taxes | B17: =MAX(0,B16*B5)
A18: WHAT YOU ACTUALLY KEPT | B18: =B16-B17
A20: Hours worked on jobs (on-site + drive) | B20: =SUM('Job Log'!G6:H65)
A21: Job profitability: average profit per hour | B21: =IF(B20>0,SUM('Job Log'!I6:I65)/B20,0)
A22: Jobs below your target profit per hour | B22: =COUNTIF('Job Log'!J6:J65,"<"&B6) | C22: Re-price or re-scope these next time.
A23: Best job (highest profit per hour) | B23: =IF(B9>0,MAX('Job Log'!J6:J65),0)
A24: Worst job (lowest profit per hour) | B24: =IF(B9>0,MIN('Job Log'!J6:J65),0)
A26: Expenses by category | B26: Amount
A27: Fuel | B27: =SUMIF(Expenses!$C$6:$C$65,A27,Expenses!$D$6:$D$65)
A28: Vehicle | B28: =SUMIF(Expenses!$C$6:$C$65,A28,Expenses!$D$6:$D$65)
A29: Insurance | B29: =SUMIF(Expenses!$C$6:$C$65,A29,Expenses!$D$6:$D$65)
A30: Supplies | B30: =SUMIF(Expenses!$C$6:$C$65,A30,Expenses!$D$6:$D$65)
A31: Equipment | B31: =SUMIF(Expenses!$C$6:$C$65,A31,Expenses!$D$6:$D$65)
A32: Software/phone | B32: =SUMIF(Expenses!$C$6:$C$65,A32,Expenses!$D$6:$D$65)
A33: Marketing | B33: =SUMIF(Expenses!$C$6:$C$65,A33,Expenses!$D$6:$D$65)
A34: Fees | B34: =SUMIF(Expenses!$C$6:$C$65,A34,Expenses!$D$6:$D$65)
A35: Helper pay | B35: =SUMIF(Expenses!$C$6:$C$65,A35,Expenses!$D$6:$D$65)
A36: Other | B36: =SUMIF(Expenses!$C$6:$C$65,A36,Expenses!$D$6:$D$65)

Sheet Job Log
A1: Job Log — every job, every week
A2: One row per job. Profit per hour is what you actually earned for your time on that job.
A3: Yellow cells are inputs — change them. Green cells are results (formulas).
A5: Date | B5: Customer | C5: Service | D5: Price charged | E5: Materials $ | F5: Other job costs $ | G5: On-site hrs | H5: Drive hrs | I5: Job profit | J5: Profit / hour
A6: 2026-01-05 | B6: Example — replace | C6: Standard clean | D6: 180 | E6: 8 | F6: 0 | G6: 3 | H6: 0.5 | I6: =IF(D6="","",D6-E6-F6) | J6: =IF(OR(D6="",G6+H6=0),"",I6/(G6+H6))
A7: 2026-01-06 | B7: Example — replace | C7: Deep clean | D7: 340 | E7: 15 | F7: 0 | G7: 5.5 | H7: 0.6 | I7: =IF(D7="","",D7-E7-F7) | J7: =IF(OR(D7="",G7+H7=0),"",I7/(G7+H7))
I8: =IF(D8="","",D8-E8-F8) | J8: =IF(OR(D8="",G8+H8=0),"",I8/(G8+H8))
I9: =IF(D9="","",D9-E9-F9) | J9: =IF(OR(D9="",G9+H9=0),"",I9/(G9+H9))
I10: =IF(D10="","",D10-E10-F10) | J10: =IF(OR(D10="",G10+H10=0),"",I10/(G10+H10))
I11: =IF(D11="","",D11-E11-F11) | J11: =IF(OR(D11="",G11+H11=0),"",I11/(G11+H11))
I12: =IF(D12="","",D12-E12-F12) | J12: =IF(OR(D12="",G12+H12=0),"",I12/(G12+H12))
I13: =IF(D13="","",D13-E13-F13) | J13: =IF(OR(D13="",G13+H13=0),"",I13/(G13+H13))
I14: =IF(D14="","",D14-E14-F14) | J14: =IF(OR(D14="",G14+H14=0),"",I14/(G14+H14))
I15: =IF(D15="","",D15-E15-F15) | J15: =IF(OR(D15="",G15+H15=0),"",I15/(G15+H15))
I16: =IF(D16="","",D16-E16-F16) | J16: =IF(OR(D16="",G16+H16=0),"",I16/(G16+H16))
I17: =IF(D17="","",D17-E17-F17) | J17: =IF(OR(D17="",G17+H17=0),"",I17/(G17+H17))
I18: =IF(D18="","",D18-E18-F18) | J18: =IF(OR(D18="",G18+H18=0),"",I18/(G18+H18))
I19: =IF(D19="","",D19-E19-F19) | J19: =IF(OR(D19="",G19+H19=0),"",I19/(G19+H19))
... I65: =IF(D65="","",D65-E65-F65) | J65: =IF(OR(D65="",G65+H65=0),"",I65/(G65+H65))

Sheet Expenses
A1: Business Expenses
A2: Everything the business spent this period that isn't tied to one job.
A3: Yellow cells are inputs — change them. Green cells are results (formulas).
A5: Date | B5: What | C5: Category | D5: Amount
A6: 2026-01-05 | B6: Fuel — example | C6: Fuel | D6: 60
A7: 2026-01-06 | B7: Supplies restock — example | C7: Supplies | D7: 45
