Workbook

Sheet Your Numbers
A1: Your Numbers — what you need to charge per billable hour
A2: Start here. Every other sheet uses the Target hourly rate from this page.
A3: Yellow cells are inputs — change them. Green cells are results (formulas).
A5: Annual take-home pay goal (what you want to pay yourself) | B5: 60000 | C5: Be honest — this is your salary, not the business's revenue.
A6: Tax set-aside (% of profit) — ask your accountant | B6: 0.25
A7: Annual business costs (vehicle, insurance, supplies, equipment, software, phone, marketing) | B7: 20000
A8: Working weeks per year (after vacation, weather, sick days) | B8: 40
A9: Billable hours per week (paid, on-site time — not driving or quoting) | B9: 25 | C9: Most solo operators bill 25–32 hours in a 45–50 hour work week.
A11: Profit needed before tax | B11: =B5/(1-B6)
A12: Revenue needed per year | B12: =B11+B7
A13: Billable hours per year | B13: =B8*B9
A14: Minimum hourly rate (break-even on your goal) | B14: =IF(B13>0,B12/B13,0)
A15: Buffer for slow weeks, callbacks, and price creep (%) | B15: 0.15
A16: TARGET HOURLY RATE (used by the other sheets) | B16: =B14*(1+B15)
A17: Revenue needed per working week | B17: =IF(B8>0,B12/B8,0)

Sheet Surface Matrix
A1: Surface Pricing Matrix
A2: Rates are starting points. Production rate = units you clean per hour including setup and rinse.
A3: Yellow cells are inputs — change them. Green cells are results (formulas).
A5: Surface | B5: Unit | C5: Low $ | D5: Target $ | E5: Units per hour | F5: Notes
A6: Concrete driveway / sidewalk | B6: sq ft | C6: 0.15 | D6: 0.25 | E6: 800 | F6: Surface cleaner; pre-treat + post-rinse
A7: Concrete patio | B7: sq ft | C7: 0.18 | D7: 0.3 | E7: 600 | F7: More edges and furniture moving
A8: Pavers — clean only | B8: sq ft | C8: 0.25 | D8: 0.4 | E8: 400 | F8: Low pressure; joint sand loss likely
A9: Pavers — clean + polymeric sand | B9: sq ft | C9: 0.9 | D9: 1.5 | E9: 150 | F9: Sand material extra
A10: House soft wash — vinyl siding | B10: sq ft wall | C10: 0.12 | D10: 0.2 | E10: 1200 | F10: Wall area ≈ house sq ft × 1.3–1.5 per story
A11: House soft wash — stucco / brick | B11: sq ft wall | C11: 0.15 | D11: 0.25 | E11: 900 | F11: Porous; more chem and rinse time
A12: Wood deck — clean + brighten | B12: sq ft | C12: 0.4 | D12: 0.75 | E12: 250 | F12: Low pressure; raised grain risk
A13: Fence — per side | B13: linear ft | C13: 1 | D13: 2 | E13: 80 | F13: 6ft privacy fence, one side
A14: Roof soft wash (trained only) | B14: sq ft | C14: 0.25 | D14: 0.45 | E14: 800 | F14: Check insurance coverage for roof work
A15: Gutter face brightening | B15: linear ft | C15: 1 | D15: 1.75 | E15: 100 | F15: Tiger stripes; no guarantee of full removal
A16: Pool deck | B16: sq ft | C16: 0.2 | D16: 0.35 | E16: 600
A17: Garage floor | B17: sq ft | C17: 0.2 | D17: 0.35 | E17: 500 | F17: Drainage plan needed
A18: Dumpster pad (commercial) | B18: each | C18: 75 | D18: 125 | E18: 2 | F18: Degreaser; wastewater rules apply
A19: Rust / oil stain treatment | B19: each | C19: 25 | D19: 75 | E19: 3 | F19: Improvement, not guaranteed removal
A21: Condition multipliers
A22: Condition | B22: Multiplier
A23: Light | B23: 1
A24: Moderate | B24: 1.2
A25: Heavy | B25: 1.4

Sheet Quote Builder
A1: Pressure Washing Quote Builder
A2: Pick surfaces, enter measured quantity and condition. Multiplier raises both price and time.
A3: Yellow cells are inputs — change them. Green cells are results (formulas).
A4: Target hourly rate | B4: ='Your Numbers'!$B$16
A5: Minimum job price | B5: 175
A6: Chemical + fuel cost per job hour | B6: 12
A8: Surface (pick) | B8: Quantity | C8: Condition | D8: Rate | E8: Line total | F8: Est. hours
A9: Concrete driveway / sidewalk | B9: 700 | C9: Moderate | D9: =IF(A9="","",VLOOKUP(A9,'Surface Matrix'!$A$6:$F$19,4,FALSE)*VLOOKUP(IF(C9="","Light",C9),'Surface Matrix'!$A$23:$B$25,2,FALSE)) | E9: =IF(A9="","",B9*D9) | F9: =IF(A9="","",B9/VLOOKUP(A9,'Surface Matrix'!$A$6:$F$19,5,FALSE)*VLOOKUP(IF(C9="","Light",C9),'Surface Matrix'!$A$23:$B$25,2,FALSE))
A10: House soft wash — vinyl siding | B10: 2600 | C10: Light | D10: =IF(A10="","",VLOOKUP(A10,'Surface Matrix'!$A$6:$F$19,4,FALSE)*VLOOKUP(IF(C10="","Light",C10),'Surface Matrix'!$A$23:$B$25,2,FALSE)) | E10: =IF(A10="","",B10*D10) | F10: =IF(A10="","",B10/VLOOKUP(A10,'Surface Matrix'!$A$6:$F$19,5,FALSE)*VLOOKUP(IF(C10="","Light",C10),'Surface Matrix'!$A$23:$B$25,2,FALSE))
A11: Rust / oil stain treatment | B11: 1 | C11: Heavy | D11: =IF(A11="","",VLOOKUP(A11,'Surface Matrix'!$A$6:$F$19,4,FALSE)*VLOOKUP(IF(C11="","Light",C11),'Surface Matrix'!$A$23:$B$25,2,FALSE)) | E11: =IF(A11="","",B11*D11) | F11: =IF(A11="","",B11/VLOOKUP(A11,'Surface Matrix'!$A$6:$F$19,5,FALSE)*VLOOKUP(IF(C11="","Light",C11),'Surface Matrix'!$A$23:$B$25,2,FALSE))
D12: =IF(A12="","",VLOOKUP(A12,'Surface Matrix'!$A$6:$F$19,4,FALSE)*VLOOKUP(IF(C12="","Light",C12),'Surface Matrix'!$A$23:$B$25,2,FALSE)) | E12: =IF(A12="","",B12*D12) | F12: =IF(A12="","",B12/VLOOKUP(A12,'Surface Matrix'!$A$6:$F$19,5,FALSE)*VLOOKUP(IF(C12="","Light",C12),'Surface Matrix'!$A$23:$B$25,2,FALSE))
D13: =IF(A13="","",VLOOKUP(A13,'Surface Matrix'!$A$6:$F$19,4,FALSE)*VLOOKUP(IF(C13="","Light",C13),'Surface Matrix'!$A$23:$B$25,2,FALSE)) | E13: =IF(A13="","",B13*D13) | F13: =IF(A13="","",B13/VLOOKUP(A13,'Surface Matrix'!$A$6:$F$19,5,FALSE)*VLOOKUP(IF(C13="","Light",C13),'Surface Matrix'!$A$23:$B$25,2,FALSE))
D14: =IF(A14="","",VLOOKUP(A14,'Surface Matrix'!$A$6:$F$19,4,FALSE)*VLOOKUP(IF(C14="","Light",C14),'Surface Matrix'!$A$23:$B$25,2,FALSE)) | E14: =IF(A14="","",B14*D14) | F14: =IF(A14="","",B14/VLOOKUP(A14,'Surface Matrix'!$A$6:$F$19,5,FALSE)*VLOOKUP(IF(C14="","Light",C14),'Surface Matrix'!$A$23:$B$25,2,FALSE))
D15: =IF(A15="","",VLOOKUP(A15,'Surface Matrix'!$A$6:$F$19,4,FALSE)*VLOOKUP(IF(C15="","Light",C15),'Surface Matrix'!$A$23:$B$25,2,FALSE)) | E15: =IF(A15="","",B15*D15) | F15: =IF(A15="","",B15/VLOOKUP(A15,'Surface Matrix'!$A$6:$F$19,5,FALSE)*VLOOKUP(IF(C15="","Light",C15),'Surface Matrix'!$A$23:$B$25,2,FALSE))
D16: =IF(A16="","",VLOOKUP(A16,'Surface Matrix'!$A$6:$F$19,4,FALSE)*VLOOKUP(IF(C16="","Light",C16),'Surface Matrix'!$A$23:$B$25,2,FALSE)) | E16: =IF(A16="","",B16*D16) | F16: =IF(A16="","",B16/VLOOKUP(A16,'Surface Matrix'!$A$6:$F$19,5,FALSE)*VLOOKUP(IF(C16="","Light",C16),'Surface Matrix'!$A$23:$B$25,2,FALSE))
D17: =IF(A17="","",VLOOKUP(A17,'Surface Matrix'!$A$6:$F$19,4,FALSE)*VLOOKUP(IF(C17="","Light",C17),'Surface Matrix'!$A$23:$B$25,2,FALSE)) | E17: =IF(A17="","",B17*D17) | F17: =IF(A17="","",B17/VLOOKUP(A17,'Surface Matrix'!$A$6:$F$19,5,FALSE)*VLOOKUP(IF(C17="","Light",C17),'Surface Matrix'!$A$23:$B$25,2,FALSE))
D18: =IF(A18="","",VLOOKUP(A18,'Surface Matrix'!$A$6:$F$19,4,FALSE)*VLOOKUP(IF(C18="","Light",C18),'Surface Matrix'!$A$23:$B$25,2,FALSE)) | E18: =IF(A18="","",B18*D18) | F18: =IF(A18="","",B18/VLOOKUP(A18,'Surface Matrix'!$A$6:$F$19,5,FALSE)*VLOOKUP(IF(C18="","Light",C18),'Surface Matrix'!$A$23:$B$25,2,FALSE))
A20: Subtotal | E20: =SUM(E9:E18) | F20: =SUM(F9:F18)+0.5 | G20: ← includes 0.5 hr setup/breakdown
A21: Bundle discount for 3+ services (%) | B21: 0
A23: QUOTED PRICE | E23: =CEILING(MAX(B5,E20*(1-B21)),5)
A24: Est. chemical + fuel cost | E24: =F20*B6
A25: Effective hourly after chemicals | E25: =IF(F20>0,(E23-E24)/F20,0)
A26: Status | E26: =IF(F20<=0.5,"",IF(E25<B4,"Below target — raise price or check production rates","OK"))

Sheet Rate Card
A1: Pressure Washing Rate Card
A2: Starting ranges only — prices vary a lot by region. Replace with your local numbers.
A4: Category | B4: Item | C4: Unit | D4: Low $ | E4: Target $ | F4: Your price $ | G4: Notes
A5: policy | B5: Minimum job | C5: job | D5: 150 | E5: 200 | G5: Covers setup, water, travel
A6: surface | B6: Concrete driveway / sidewalk | C6: sq ft | D6: 0.15 | E6: 0.25 | G6: Surface cleaner; pre-treat + post-rinse
A7: surface | B7: Concrete patio | C7: sq ft | D7: 0.18 | E7: 0.3 | G7: More edges and furniture moving
A8: surface | B8: Pavers — clean only | C8: sq ft | D8: 0.25 | E8: 0.4 | G8: Low pressure; joint sand loss likely
A9: surface | B9: Pavers — clean + polymeric sand | C9: sq ft | D9: 0.9 | E9: 1.5 | G9: Sand material extra
A10: surface | B10: House soft wash — vinyl siding | C10: sq ft wall | D10: 0.12 | E10: 0.2 | G10: Wall area ≈ house sq ft × 1.3–1.5 per story
A11: surface | B11: House soft wash — stucco / brick | C11: sq ft wall | D11: 0.15 | E11: 0.25 | G11: Porous; more chem and rinse time
A12: surface | B12: Wood deck — clean + brighten | C12: sq ft | D12: 0.4 | E12: 0.75 | G12: Low pressure; raised grain risk
A13: surface | B13: Fence — per side | C13: linear ft | D13: 1 | E13: 2 | G13: 6ft privacy fence, one side
A14: surface | B14: Roof soft wash (trained only) | C14: sq ft | D14: 0.25 | E14: 0.45 | G14: Check insurance coverage for roof work
A15: surface | B15: Gutter face brightening | C15: linear ft | D15: 1 | E15: 1.75 | G15: Tiger stripes; no guarantee of full removal
A16: surface | B16: Pool deck | C16: sq ft | D16: 0.2 | E16: 0.35
A17: surface | B17: Garage floor | C17: sq ft | D17: 0.2 | E17: 0.35 | G17: Drainage plan needed
A18: surface | B18: Dumpster pad (commercial) | C18: each | D18: 75 | E18: 125 | G18: Degreaser; wastewater rules apply
A19: surface | B19: Rust / oil stain treatment | C19: each | D19: 25 | E19: 75 | G19: Improvement, not guaranteed removal
A20: policy | B20: Water not available on site | C20: job | D20: 50 | E20: 100 | G20: If you must bring water
